{
  "appgroup_id": "6a021f99ac68760cbbc310db",
  "appgroup_name": "Test",
  "apps": {
    "test": {
      "app_id": "6a021f8f51c0cac6488e2325",
      "name": "Test",
      "main": false,
      "controls": {
        "vorname": {
          "identifier": "vorname",
          "label": "Vorname",
          "type": "string",
          "subtype": "text",
          "fulltype": "string/text",
          "description": "A string value not longer than 4000 characters (or `null`/`None`).",
          "required": null,
          "in_list": true,
          "in_mobile_list": true,
          "in_text": true,
          "in_structured_search": false,
          "in_fulltext_search": true,
          "in_expert_search": true
        },
        "nachname": {
          "identifier": "nachname",
          "label": "Nachname",
          "type": "string",
          "subtype": "text",
          "fulltype": "string/text",
          "description": "A string value not longer than 4000 characters (or `null`/`None`).",
          "required": null,
          "in_list": true,
          "in_mobile_list": true,
          "in_text": true,
          "in_structured_search": false,
          "in_fulltext_search": true,
          "in_expert_search": true
        },
        "email": {
          "identifier": "email",
          "label": "E-Mail-Adresse",
          "type": "string",
          "subtype": "email",
          "fulltype": "string/email",
          "description": "A valid email address (or `null`/`None`).",
          "required": null,
          "in_list": true,
          "in_mobile_list": false,
          "in_text": false,
          "in_structured_search": false,
          "in_fulltext_search": true,
          "in_expert_search": true
        },
        "nachricht": {
          "identifier": "nachricht",
          "label": "Nachricht",
          "type": "string",
          "subtype": "textarea",
          "fulltype": "string/textarea",
          "description": "A string value that can contain multiple lines of text (or `null`/`None`).",
          "required": null,
          "in_list": true,
          "in_mobile_list": false,
          "in_text": false,
          "in_structured_search": false,
          "in_fulltext_search": true,
          "in_expert_search": true
        }
      }
    }
  },
  "metadata": {
    "apps_list": [
      "Test"
    ]
  }
}